true_lies/__init__.py
true_lies/config.py
true_lies/conversation.py
true_lies/extractors.py
true_lies/html_reporter.py
true_lies/polarity.py
true_lies/runner.py
true_lies/scenario.py
true_lies/semantic.py
true_lies/utils.py
true_lies/validation_core.py
true_lies/semantic_data/banking.json
true_lies/semantic_data/energy.json
true_lies/semantic_data/insurance.json
true_lies/semantic_data/motorcycle_dealership.json
true_lies/semantic_data/retail.json
true_lies_validator-0.9.3.dist-info/licenses/LICENSE
true_lies_validator-0.9.3.dist-info/METADATA
true_lies_validator-0.9.3.dist-info/WHEEL
true_lies_validator-0.9.3.dist-info/top_level.txt
true_lies_validator-0.9.3.dist-info/RECORD
