Metadata-Version: 2.4
Name: true-lies-validator
Version: 0.9.3
Summary: True Lies - Separating truth from AI fiction. A powerful library for detecting LLM hallucinations, validating AI responses, and generating professional HTML reports with interactive dashboards.
Author: Pato Miner
Author-email: Pato Miner <patominer@gmail.com>
Keywords: llm,validation,hallucination-detection,ai,python,truth-detection,html-reports,dashboard,chatbot-testing
Classifier: Programming Language :: Python :: 3
Classifier: License :: OSI Approved :: MIT License
Classifier: Operating System :: OS Independent
Classifier: Development Status :: 4 - Beta
Classifier: Intended Audience :: Developers
Classifier: Topic :: Scientific/Engineering :: Artificial Intelligence
Requires-Python: >=3.10
License-File: LICENSE
Dynamic: author
Dynamic: license-file
Dynamic: requires-python
